biorun/__about__.py
biorun/__init__.py
biorun/__main__.py
biorun/align.py
biorun/code.py
biorun/combine.py
biorun/comm.py
biorun/convert.py
biorun/enrichr.py
biorun/fasta.py
biorun/fetch.py
biorun/format.py
biorun/gff.py
biorun/gprof.py
biorun/gtf.py
biorun/jsonrec.py
biorun/main.py
biorun/mart.py
biorun/meta.py
biorun/models.py
biorun/mygene.py
biorun/ontology.py
biorun/parser.py
biorun/patterns.py
biorun/search.py
biorun/search2.py
biorun/table.py
biorun/taxon.py
biorun/test.py
biorun/uniq.py
biorun/utils.py
biorun/variant.py
biorun/vcf2fasta.py
biorun/api/__init__.py
biorun/api/ena.py
biorun/api/ena_fastq.py
biorun/api/ncbi_datasets.py
biorun/data/BLASTN
biorun/data/alias.txt
biorun/data/align_default.diff
biorun/data/align_default.txt
biorun/data/align_default.vcf
biorun/data/align_global.txt
biorun/data/align_input.fa
biorun/data/align_input.vcf
biorun/data/align_local.txt
biorun/data/align_pile1.txt
biorun/data/align_s.tsv
biorun/data/align_s.txt
biorun/data/align_s.vcf
biorun/data/comm0.txt
biorun/data/comm1.txt
biorun/data/comm2.txt
biorun/data/explain_exon.txt
biorun/data/explain_food.txt
biorun/data/explain_neutral.txt
biorun/data/fasta_alias1.fa
biorun/data/fasta_all1.fa
biorun/data/fasta_all2.fa
biorun/data/fasta_all3.fa
biorun/data/fasta_all4.fa
biorun/data/fasta_cds.fa
biorun/data/fasta_frame.fa
biorun/data/fasta_ids.fa
biorun/data/fasta_match.fa
biorun/data/fasta_multi.fa
biorun/data/fasta_olap1.fa
biorun/data/fasta_protein.fa
biorun/data/fasta_rename1.fa
biorun/data/fasta_s.fa
biorun/data/fasta_start.fa
biorun/data/fasta_stop.fa
biorun/data/fasta_translate.fa
biorun/data/fetch_enst.txt
biorun/data/fetch_gff.gff
biorun/data/fetch_prot.fa
biorun/data/file1.txt
biorun/data/file2.txt
biorun/data/format_mafft1.diff.txt
biorun/data/format_mafft1.txt
biorun/data/format_mafft1.vcf
biorun/data/genomes.fa
biorun/data/genomes.gb
biorun/data/genomes.json
biorun/data/genomes.jsonl
biorun/data/gff_CDS.gff
biorun/data/gff_all.gff
biorun/data/gff_olap1.gff
bio-1.8.0.dist-info/METADATA
bio-1.8.0.dist-info/WHEEL
bio-1.8.0.dist-info/entry_points.txt
bio-1.8.0.dist-info/licenses/LICENSE
bio-1.8.0.dist-info/RECORD
