Metadata-Version: 2.4
Name: bio
Version: 1.8.0
Project-URL: Documentation, https://github.com/ialbert/bio#readme
Project-URL: Issues, https://github.com/ialbert/bio/issues
Project-URL: Source, https://github.com/ialbert/bio/
Author-email: Istvan Albert <istvan.albert@gmail.com>
License-Expression: MIT
License-File: LICENSE
Classifier: Development Status :: 4 - Beta
Classifier: Programming Language :: Python
Classifier: Programming Language :: Python :: 3.10
Classifier: Programming Language :: Python :: 3.11
Classifier: Programming Language :: Python :: 3.12
Requires-Python: >=3.10
Requires-Dist: biopython>=1.80
Requires-Dist: gprofiler-official
Requires-Dist: mygene
Requires-Dist: pandas
Requires-Dist: pooch
Requires-Dist: requests
Requires-Dist: tqdm
